.gitignore
DONE.txt
FRIENDS.md
LICENSE
README.md
TODO.txt
setup.py
test.html
docs/Makefile
docs/requirements.txt
docs/screenshot_00.png
docs/screenshot_01.png
docs/screenshot_02.png
docs/screenshot_03.png
docs/screenshot_04.png
docs/build/.gitkeep
docs/source/conf.py
docs/source/index.rst
docs/source/modules.rst
docs/source/terminedia.rst
docs/source/images/example_00.png
terminedia/__init__.py
terminedia/asynchronous.py
terminedia/backend_common.py
terminedia/contexts.py
terminedia/drawing.py
terminedia/events.py
terminedia/html.py
terminedia/image.py
terminedia/input.py
terminedia/screen.py
terminedia/sprites.py
terminedia/subpixels.py
terminedia/terminal.py
terminedia/unicode.py
terminedia/unicode_transforms.py
terminedia/values.py
terminedia/widgets.py
terminedia.egg-info/PKG-INFO
terminedia.egg-info/SOURCES.txt
terminedia.egg-info/dependency_links.txt
terminedia.egg-info/entry_points.txt
terminedia.egg-info/requires.txt
terminedia.egg-info/top_level.txt
terminedia.egg-info/zip-safe
terminedia/data/__init__.py
terminedia/data/unscii-16-full.hex
terminedia/data/unscii-8-fantasy.hex
terminedia/data/unscii-8-mcr.hex
terminedia/data/unscii-8-thin.hex
terminedia/data/unscii-8.hex
terminedia/examples/__init__.py
terminedia/examples/bezier.py
terminedia/examples/butterfly.gif
terminedia/examples/butterfly.jpg
terminedia/examples/butterfly_bw.tiff
terminedia/examples/context.py
terminedia/examples/effects.py
terminedia/examples/ellipses.py
terminedia/examples/image.py
terminedia/examples/lines.py
terminedia/examples/looptest.py
terminedia/examples/moon_ascii_bw.pgm
terminedia/examples/moon_ascii_color.ppm
terminedia/examples/moon_bin_bw.pgm
terminedia/examples/moon_bin_color.pnm
terminedia/examples/mousesnippet.py
terminedia/examples/plot.py
terminedia/examples/shapes.py
terminedia/examples/simple_gradient_transformer.py
terminedia/examples/simple_sprite.py
terminedia/examples/simple_transformer.py
terminedia/examples/simple_transformer_colors_to_chars.py
terminedia/examples/snake.py
terminedia/examples/text.py
terminedia/text/__init__.py
terminedia/text/fonts.py
terminedia/text/planes.py
terminedia/text/style.py
terminedia/transformers/__init__.py
terminedia/transformers/_kernel_table_ascii.py
