Metadata-Version: 2.1
Name: terminedia
Version: 0.4.1
Summary: Utilities for drawing and interactiveness at the terminal
Home-page: https://github.com/jsbueno/terminedia
Author: João S. O. Bueno
Author-email: gwidion@gmail.com
License: LGPLv3+
Project-URL: Documentation, https://terminedia.readthedocs.io/en/stable/
Project-URL: Source Code, https://github.com/jsbueno/terminedia
Keywords: terminal cmd posix xterm ANSI color
Platform: UNKNOWN
Classifier: Development Status :: 4 - Beta
Classifier: Intended Audience :: Developers
Classifier: Intended Audience :: System Administrators
Classifier: Programming Language :: Python :: 3.6
Classifier: Programming Language :: Python :: 3.7
Classifier: Programming Language :: Python :: 3.8
Classifier: Programming Language :: Python :: 3.9
Classifier: Programming Language :: Python :: 3.10
Classifier: Programming Language :: Python :: Implementation :: PyPy
Classifier: License :: OSI Approved :: GNU Lesser General Public License v3 or later (LGPLv3+)
Classifier: License :: OSI Approved :: GNU General Public License v3 or later (GPLv3+)
Classifier: Operating System :: OS Independent
Classifier: Topic :: Artistic Software
Classifier: Topic :: Multimedia :: Graphics
Classifier: Topic :: Terminals
Classifier: Topic :: Terminals :: Terminal Emulators/X Terminals
Provides-Extra: doc
Provides-Extra: tests
Provides-Extra: images
